odoo8_addon_mgmtsystem_quality-8.0.1.0.0-py2.7-nspkg.pth
odoo_addons/mgmtsystem_quality/__openerp__.py
odoo_addons/mgmtsystem_quality/__init__.py
odoo_addons/mgmtsystem_quality/README.rst
odoo_addons/mgmtsystem_quality/i18n/mgmtsystem_quality.pot
odoo_addons/mgmtsystem_quality/i18n/nb.po
odoo_addons/mgmtsystem_quality/i18n/de.po
odoo_addons/mgmtsystem_quality/i18n/vi.po
odoo_addons/mgmtsystem_quality/i18n/fr.po
odoo_addons/mgmtsystem_quality/i18n/pt_BR.po
odoo_addons/mgmtsystem_quality/i18n/sv.po
odoo_addons/mgmtsystem_quality/data/mgmtsystem_system.xml
odoo_addons/mgmtsystem_quality/static/description/icon.png
odoo8_addon_mgmtsystem_quality-8.0.1.0.0.dist-info/top_level.txt
odoo8_addon_mgmtsystem_quality-8.0.1.0.0.dist-info/WHEEL
odoo8_addon_mgmtsystem_quality-8.0.1.0.0.dist-info/RECORD
odoo8_addon_mgmtsystem_quality-8.0.1.0.0.dist-info/metadata.json
odoo8_addon_mgmtsystem_quality-8.0.1.0.0.dist-info/DESCRIPTION.rst
odoo8_addon_mgmtsystem_quality-8.0.1.0.0.dist-info/METADATA
odoo8_addon_mgmtsystem_quality-8.0.1.0.0.dist-info/namespace_packages.txt
